.travis.yml
AUTHORS.rst
HISTORY.rst
LICENSE.txt
MANIFEST.in
README.rst
TODO.rst
requirements.txt
setup.cfg
setup.py
tox.ini
odscharts/ElementTree_27OD.py
odscharts/ElementTree_34OD.py
odscharts/__init__.py
odscharts/_version.py
odscharts/color_utils.py
odscharts/data_table_desc.py
odscharts/find_obj.py
odscharts/line_styles.py
odscharts/metainf.py
odscharts/object_content.py
odscharts/plot_table_desc.py
odscharts/spreadsheet.py
odscharts/template_xml_file.py
odscharts/xml_set_rep.py
odscharts.egg-info/PKG-INFO
odscharts.egg-info/SOURCES.txt
odscharts.egg-info/dependency_links.txt
odscharts.egg-info/not-zip-safe
odscharts.egg-info/requires.txt
odscharts.egg-info/top_level.txt
odscharts/examples/alt_vs_press.py
odscharts/examples/bmi_index.py
odscharts/examples/line_styles.py
odscharts/examples/metabolic.py
odscharts/examples/trig_funcs.py
odscharts/templates/alt_chart.ods
odscharts/templates/alt_chart_y2.ods
odscharts/templates/empty_sheets123.ods
odscharts/tests/__init__.py
odscharts/tests/test_sheet.py